dlp_wrapper/__init__.py
dlp_wrapper/dlp_wrapper.py
dlp_wrapper-0.1.0.dist-info/METADATA
dlp_wrapper-0.1.0.dist-info/WHEEL
dlp_wrapper-0.1.0.dist-info/RECORD
