Metadata-Version: 2.1
Name: dlp_wrapper
Version: 0.1.0
Summary: Wrapper for yt-dlp, designed to download audio or video from provided URLs. 
License: MIT
Author: RobertHue
Author-email: robert.huem@gmail.com
Requires-Python: >=3.12,<4.0
Classifier: License :: OSI Approved :: MIT License
Classifier: Programming Language :: Python :: 3
Classifier: Programming Language :: Python :: 3.12
Requires-Dist: yt-dlp (>=2024.8.1,<2025.0.0)
